PythonTornadoJieshao/README.md
PythonTornadoJieshao/__init__.py
PythonTornadoJieshao/__main__.py
PythonTornadoJieshao/file.epub
PythonTornadoJieshao/index.html
PythonTornadoJieshao/css/__init__.py
PythonTornadoJieshao/css/annotations.css
PythonTornadoJieshao/css/main.css
PythonTornadoJieshao/css/normalize.css
PythonTornadoJieshao/css/popup.css
PythonTornadoJieshao/font/__init__.py
PythonTornadoJieshao/font/fontello.eot
PythonTornadoJieshao/font/fontello.svg
PythonTornadoJieshao/font/fontello.ttf
PythonTornadoJieshao/font/fontello.woff
PythonTornadoJieshao/img/__init__.py
PythonTornadoJieshao/img/annotator-glyph-sprite.png
PythonTornadoJieshao/img/annotator-icon-sprite.png
PythonTornadoJieshao/img/apple-touch-icon.png
PythonTornadoJieshao/img/cancelfullscreen.png
PythonTornadoJieshao/img/close.png
PythonTornadoJieshao/img/fullscreen.png
PythonTornadoJieshao/img/loader.gif
PythonTornadoJieshao/img/menu-icon.png
PythonTornadoJieshao/img/save.png
PythonTornadoJieshao/img/saved.png
PythonTornadoJieshao/img/settings-s.png
PythonTornadoJieshao/img/settings.png
PythonTornadoJieshao/img/star.png
PythonTornadoJieshao/js/__init__.py
PythonTornadoJieshao/js/epub.js
PythonTornadoJieshao/js/epub.min.js
PythonTornadoJieshao/js/epub.min.map
PythonTornadoJieshao/js/hooks.min.js
PythonTornadoJieshao/js/hooks.min.map
PythonTornadoJieshao/js/reader.js
PythonTornadoJieshao/js/reader.js.map
PythonTornadoJieshao/js/reader.min.js
PythonTornadoJieshao/js/reader.min.map
PythonTornadoJieshao/js/hooks/__init__.py
PythonTornadoJieshao/js/hooks/extensions/__init__.py
PythonTornadoJieshao/js/hooks/extensions/highlight.js
PythonTornadoJieshao/js/libs/__init__.py
PythonTornadoJieshao/js/libs/jquery.min.js
PythonTornadoJieshao/js/libs/localforage.min.js
PythonTornadoJieshao/js/libs/screenfull.js
PythonTornadoJieshao/js/libs/screenfull.min.js
PythonTornadoJieshao/js/libs/zip.min.js
PythonTornadoJieshao/js/plugins/__init__.py
PythonTornadoJieshao/js/plugins/hypothesis.js
python_tornado_jieshao-2024.3.1.0.dist-info/METADATA
python_tornado_jieshao-2024.3.1.0.dist-info/WHEEL
python_tornado_jieshao-2024.3.1.0.dist-info/entry_points.txt
python_tornado_jieshao-2024.3.1.0.dist-info/top_level.txt
python_tornado_jieshao-2024.3.1.0.dist-info/RECORD
